openstack_requirements/__init__.py
openstack_requirements/constraints.py
openstack_requirements/project.py
openstack_requirements/project_config.py
openstack_requirements/requirement.py
openstack_requirements/cmds/__init__.py
openstack_requirements/cmds/check_conflicts.py
openstack_requirements/cmds/check_exists.py
openstack_requirements/cmds/check_py2.py
openstack_requirements/cmds/edit_constraint.py
openstack_requirements/cmds/generate.py
openstack_requirements/cmds/normalize_requirements.py
openstack_requirements/cmds/update.py
openstack_requirements/cmds/validate.py
openstack_requirements/cmds/validate_projects.py
openstack_requirements/tests/__init__.py
openstack_requirements/tests/common.py
openstack_requirements/tests/test_check_constraints.py
openstack_requirements/tests/test_constraints.py
openstack_requirements/tests/test_edit_constraint.py
openstack_requirements/tests/test_generate.py
openstack_requirements/tests/test_project.py
openstack_requirements/tests/test_requirement.py
openstack_requirements/tests/test_update.py
openstack_requirements/tests/test_update_pbr.py
openstack_requirements/tests/test_update_suffix.py
openstack_requirements/tests/files/blacklist.txt
openstack_requirements/tests/files/gr-base.txt
openstack_requirements/tests/files/old-setup.py
openstack_requirements/tests/files/pbr_setup.cfg
openstack_requirements/tests/files/project-with-bad-requirement.txt
openstack_requirements/tests/files/project-with-oslo-tar.txt
openstack_requirements/tests/files/project.txt
openstack_requirements/tests/files/setup.cfg
openstack_requirements/tests/files/setup.py
openstack_requirements/tests/files/test-project.txt
openstack_requirements/tests/files/upper-constraints.txt
openstack_requirements-1.2.0.dist-info/DESCRIPTION.rst
openstack_requirements-1.2.0.dist-info/METADATA
openstack_requirements-1.2.0.dist-info/RECORD
openstack_requirements-1.2.0.dist-info/WHEEL
openstack_requirements-1.2.0.dist-info/entry_points.txt
openstack_requirements-1.2.0.dist-info/metadata.json
openstack_requirements-1.2.0.dist-info/pbr.json
openstack_requirements-1.2.0.dist-info/top_level.txt
