Metadata-Version: 2.0
Name: openstack-requirements
Version: 1.2.0
Summary: OpenStack python dependency management tools
Home-page: https://docs.openstack.org/requirements/latest/
Author: OpenStack
Author-email: openstack-dev@lists.openstack.org
License: UNKNOWN
Platform: UNKNOWN
Classifier: Environment :: OpenStack
Classifier: Intended Audience :: Information Technology
Classifier: Intended Audience :: System Administrators
Classifier: License :: OSI Approved :: Apache Software License
Classifier: Operating System :: POSIX :: Linux
Classifier: Operating System :: Microsoft :: Windows
Classifier: Operating System :: MacOS :: MacOS X
Classifier: Programming Language :: Python
Classifier: Programming Language :: Python :: 2
Classifier: Programming Language :: Python :: 2.7
Classifier: Programming Language :: Python :: 3
Classifier: Programming Language :: Python :: 3.4
Classifier: Programming Language :: Python :: 3.5
Requires-Dist: fixtures (>=3.0.0)
Requires-Dist: Parsley (>=1.2)
Requires-Dist: six (>=1.10.0)
Requires-Dist: packaging (>=16.5)
Requires-Dist: requests (>=2.14.2)
Requires-Dist: PyYAML (>=3.10)
